testplans/__init__.py
testplans/_results.py
testplans/api.py
testplans/devices.py
testplans/gui.py
testplans/main.py
testplans/models.py
testplans/tc.py
testplans/tc_groups.py
testplans/tm.py
testplans/types.py
testplans-0.4.34.dist-info/LICENSE
testplans-0.4.34.dist-info/METADATA
testplans-0.4.34.dist-info/WHEEL
testplans-0.4.34.dist-info/top_level.txt
testplans-0.4.34.dist-info/RECORD
